oifits.py
oifits-0.6.1.dist-info/LICENSE.txt
oifits-0.6.1.dist-info/WHEEL
oifits-0.6.1.dist-info/METADATA
oifits-0.6.1.dist-info/RECORD
