Metadata-Version: 2.3
Name: oifits
Version: 0.6.1
Summary: A module for reading/writing OIFITS (v1, v2) files
Keywords: astronomy,interferometry
Author-email: Paul Boley <pboley@gmail.com>
Requires-Python: >=3.8
Requires-Dist: astropy>=4.2
Requires-Dist: numpy>=1.19.2
Project-URL: Home, https://github.com/pboley/oifits
